blue_fusion/README.py
blue_fusion/__init__.py
blue_fusion/__main__.py
blue_fusion/config.env
blue_fusion/env.py
blue_fusion/functions.py
blue_fusion/host.py
blue_fusion/logger.py
blue_fusion/sample.env
blue_fusion/urls.py
blue_fusion/.abcli/abcli.sh
blue_fusion/.abcli/actions.sh
blue_fusion/.abcli/aka.sh
blue_fusion/.abcli/alias.sh
blue_fusion/.abcli/blue_fusion.sh
blue_fusion/.abcli/bright.sh
blue_fusion/.abcli/browse.sh
blue_fusion/.abcli/install.sh
blue_fusion/.abcli/bright/browse.sh
blue_fusion/.abcli/bright/install.sh
blue_fusion/.abcli/tests/README.sh
blue_fusion/.abcli/tests/help.sh
blue_fusion/.abcli/tests/version.sh
blue_fusion/help/__init__.py
blue_fusion/help/__main__.py
blue_fusion/help/bright.py
blue_fusion/help/functions.py
blue_fusion-4.16.1.dist-info/LICENSE
blue_fusion-4.16.1.dist-info/METADATA
blue_fusion-4.16.1.dist-info/WHEEL
blue_fusion-4.16.1.dist-info/top_level.txt
blue_fusion-4.16.1.dist-info/RECORD
